Metadata-Version: 2.1
Name: target-typo
Version: 0.1.0
Summary: Typo is the intelligent data quality barrier for enterprise information systems. The Typo target communicates with Singer taps, and consumes data that conforms to the Singer JSON specification.
Home-page: https://www.typo.ai/
Author: Typo
License: Apache 2.0
Keywords: typo.ai data quality singer target
Platform: UNKNOWN
Classifier: Development Status :: 4 - Beta
Classifier: Intended Audience :: Developers
Classifier: Intended Audience :: Information Technology
Classifier: Intended Audience :: System Administrators
Classifier: License :: OSI Approved :: Apache Software License
Classifier: Operating System :: OS Independent
Classifier: Programming Language :: Python :: 3 :: Only
Classifier: Programming Language :: Python :: 3
Classifier: Programming Language :: Python :: 3.6
Classifier: Topic :: Database :: Database Engines/Servers
Classifier: Topic :: Scientific/Engineering :: Information Analysis
Classifier: Topic :: Scientific/Engineering :: Artificial Intelligence
Requires-Dist: singer-python (>=5.0.12)
Requires-Dist: requests (>=2.21.0)
Requires-Dist: jsonschema (<3.0a,>=2.6.0)
